graphpkg/__init__.py
graphpkg/live/__init__.py
graphpkg/live/_dashboard.py
graphpkg/live/_graph.py
graphpkg/static/__init__.py
graphpkg/static/_general.py
graphpkg/static/_ts.py
graphpkg-1.0.4.dist-info/AUTHORS.rst
graphpkg-1.0.4.dist-info/LICENSE.txt
graphpkg-1.0.4.dist-info/METADATA
graphpkg-1.0.4.dist-info/WHEEL
graphpkg-1.0.4.dist-info/top_level.txt
graphpkg-1.0.4.dist-info/RECORD
